<annotation>
	<folder>mix_480x800</folder>
	<filename>101.jpg</filename>
	<path>C:\Users\Yavac\Desktop\images_components\radio_button\mix_480x800\101.jpg</path>
	<source>
		<database>Unknown</database>
	</source>
	<size>
		<width>480</width>
		<height>800</height>
		<depth>3</depth>
	</size>
	<segmented>0</segmented>
	<object>
		<name>radio_button</name>
		<pose>Unspecified</pose>
		<truncated>0</truncated>
		<difficult>0</difficult>
		<bndbox>
			<xmin>3</xmin>
			<ymin>22</ymin>
			<xmax>30</xmax>
			<ymax>51</ymax>
		</bndbox>
	</object>
	<object>
		<name>radio_button</name>
		<pose>Unspecified</pose>
		<truncated>0</truncated>
		<difficult>0</difficult>
		<bndbox>
			<xmin>39</xmin>
			<ymin>24</ymin>
			<xmax>91</xmax>
			<ymax>82</ymax>
		</bndbox>
	</object>
	<object>
		<name>radio_button</name>
		<pose>Unspecified</pose>
		<truncated>0</truncated>
		<difficult>0</difficult>
		<bndbox>
			<xmin>111</xmin>
			<ymin>30</ymin>
			<xmax>213</xmax>
			<ymax>143</ymax>
		</bndbox>
	</object>
	<object>
		<name>radio_button</name>
		<pose>Unspecified</pose>
		<truncated>0</truncated>
		<difficult>0</difficult>
		<bndbox>
			<xmin>255</xmin>
			<ymin>43</ymin>
			<xmax>457</xmax>
			<ymax>264</ymax>
		</bndbox>
	</object>
	<object>
		<name>radio_button</name>
		<pose>Unspecified</pose>
		<truncated>0</truncated>
		<difficult>0</difficult>
		<bndbox>
			<xmin>65</xmin>
			<ymin>335</ymin>
			<xmax>445</xmax>
			<ymax>752</ymax>
		</bndbox>
	</object>
</annotation>
