<annotation>
	<folder>mix_480x800</folder>
	<filename>888.jpg</filename>
	<path>C:\Users\Yavac\Desktop\images_components\601-900_list_view\mix_480x800\888.jpg</path>
	<source>
		<database>Unknown</database>
	</source>
	<size>
		<width>480</width>
		<height>800</height>
		<depth>3</depth>
	</size>
	<segmented>0</segmented>
	<object>
		<name>list_view</name>
		<pose>Unspecified</pose>
		<truncated>1</truncated>
		<difficult>0</difficult>
		<bndbox>
			<xmin>8</xmin>
			<ymin>457</ymin>
			<xmax>480</xmax>
			<ymax>675</ymax>
		</bndbox>
	</object>
	<object>
		<name>list_view</name>
		<pose>Unspecified</pose>
		<truncated>0</truncated>
		<difficult>0</difficult>
		<bndbox>
			<xmin>227</xmin>
			<ymin>107</ymin>
			<xmax>478</xmax>
			<ymax>223</ymax>
		</bndbox>
	</object>
	<object>
		<name>list_view</name>
		<pose>Unspecified</pose>
		<truncated>0</truncated>
		<difficult>0</difficult>
		<bndbox>
			<xmin>98</xmin>
			<ymin>63</ymin>
			<xmax>223</xmax>
			<ymax>123</ymax>
		</bndbox>
	</object>
	<object>
		<name>list_view</name>
		<pose>Unspecified</pose>
		<truncated>0</truncated>
		<difficult>0</difficult>
		<bndbox>
			<xmin>33</xmin>
			<ymin>40</ymin>
			<xmax>96</xmax>
			<ymax>72</ymax>
		</bndbox>
	</object>
	<object>
		<name>list_view</name>
		<pose>Unspecified</pose>
		<truncated>1</truncated>
		<difficult>0</difficult>
		<bndbox>
			<xmin>1</xmin>
			<ymin>30</ymin>
			<xmax>32</xmax>
			<ymax>46</ymax>
		</bndbox>
	</object>
</annotation>
